{
    "World": {
        "x": 1800,
        "y": 600
    },

    "Player": {
        "x": 32,
        "y": 450
    },

    "Background": [{
            "x": 0,
            "y": 0,
            "height": 600,
            "width": 800,
            "src": "SF",
            "tile": true
        },
        {
            "x": 30,
            "y": 505,
            "height": 60,
            "width": 35,
            "src": "door",
            "tile": false
        }, {
            "x": 3700,
            "y": 505,
            "height": 60,
            "width": 35,
            "src": "door",
            "tile": false
        }
    ],

    "FlagPole": {},

    "Ground": [{
        "start_x": 3600,
        "end_x": 3900,
        "height": 560,
        "src": "ground"
    }, {
        "start_x": 0,
        "end_x": 400,
        "height": 560,
        "src": "ground"
    }],

    "Platform": [],

    "QBlocks": [{
        "x": 102,
        "y": 450,
        "powerUp": "coffee"
    }],

    "Bricks": [{
            "x": 70,
            "y": 450,
            "counter": 1
        },
        {
            "x": 134,
            "y": 450,
            "counter": 5
        }
    ],

    "Eswitch": {
        "x": 250,
        "y": 528
    },

    "ESCoins": [{
            "x": 1100,
            "y": 350
        }, {
            "x": 1132,
            "y": 350
        }, {
            "x": 1164,
            "y": 350
        },

        {
            "x": 300,
            "y": 200
        }, {
            "x": 332,
            "y": 200
        }, {
            "x": 364,
            "y": 200
        }
    ],

    "Toike": [{
        "x": 200,
        "y": 100
    }],

    "Enemies": [{
        "src": "goomba",
        "x": 2200,
        "y": 398,
        "tween_x": 2268,
        "tween_y": 398,
        "tween_speed": 3000,
        "animate": [{
            "name": "walk",
            "frames": [0, 1, 2],
            "delay": 4,
            "play": true
        }],
        "lazer": false,
        "static": false
    }]
}